hellopip/__init__.py
hellopip/hellopip.py
tests/__init__.py
tests/test_all.py
hellopippkg-0.0.3.dist-info/LICENSE
hellopippkg-0.0.3.dist-info/METADATA
hellopippkg-0.0.3.dist-info/WHEEL
hellopippkg-0.0.3.dist-info/top_level.txt
hellopippkg-0.0.3.dist-info/RECORD
