Metadata-Version: 2.1
Name: hellopippkg
Version: 0.0.3
Summary: Simply display HELLO PIP!!
Home-page: UNKNOWN
License: UNKNOWN
Platform: UNKNOWN
Classifier: Programming Language :: Python :: 3.7
Classifier: Operating System :: OS Independent
